cultcargo/MANIFEST.stimela
cultcargo/__init__.py
cultcargo/aimfast.yml
cultcargo/astropy.yml
cultcargo/bdsf.yml
cultcargo/breizorro.yml
cultcargo/builder/build_cargo.py
cultcargo/builder/build_utils.py
cultcargo/builder/cargo-manifest.yml
cultcargo/casa/__init__.py
cultcargo/casa/bandpass.yml
cultcargo/casa/calibration.yml
cultcargo/casa/clearcal.yml
cultcargo/casa/concat.yml
cultcargo/casa/flag.yml
cultcargo/casa/importgmrt.yml
cultcargo/casa/listobs.yml
cultcargo/casa/mstransform.yml
cultcargo/casa/plotants.yml
cultcargo/casa/plotms.yml
cultcargo/casa/polcal.yml
cultcargo/casa/setjy.yml
cultcargo/casa/split.yml
cultcargo/chgcentre.yml
cultcargo/crystalball.yml
cultcargo/cubical.yml
cultcargo/fitstool.yml
cultcargo/genesis/__init__.py
cultcargo/genesis/breizorro/breizorro.yaml
cultcargo/genesis/casa/casa-inputs.yml
cultcargo/genesis/cubical/__init__.py
cultcargo/genesis/cubical/make_stimela_schema.py
cultcargo/genesis/cubical/schema.yaml
cultcargo/genesis/cubical/schema_JONES_TEMPLATE.yaml
cultcargo/genesis/cult-cargo-base.yml
cultcargo/genesis/meqtrees/__init__.py
cultcargo/genesis/pfb-imaging/latest/cgopts.yml
cultcargo/genesis/pfb-imaging/latest/degrid.yaml
cultcargo/genesis/pfb-imaging/latest/dist.yml
cultcargo/genesis/pfb-imaging/latest/fluxtractor.yaml
cultcargo/genesis/pfb-imaging/latest/grid.yaml
cultcargo/genesis/pfb-imaging/latest/gridding.yml
cultcargo/genesis/pfb-imaging/latest/hci.yaml
cultcargo/genesis/pfb-imaging/latest/init.yaml
cultcargo/genesis/pfb-imaging/latest/kclean.yaml
cultcargo/genesis/pfb-imaging/latest/model2comps.yaml
cultcargo/genesis/pfb-imaging/latest/out.yml
cultcargo/genesis/pfb-imaging/latest/pdopts.yml
cultcargo/genesis/pfb-imaging/latest/pmopts.yml
cultcargo/genesis/pfb-imaging/latest/restore.yaml
cultcargo/genesis/pfb-imaging/latest/sara.yaml
cultcargo/genesis/pfb-imaging/latest/smoovie.yaml
cultcargo/genesis/pfb-imaging/latest/spotless.yaml
cultcargo/genesis/pfb-imaging/latest/uncabbedcabs.yml
cult_cargo-0.2.0.dist-info/LICENSE
cult_cargo-0.2.0.dist-info/METADATA
cult_cargo-0.2.0.dist-info/WHEEL
cult_cargo-0.2.0.dist-info/entry_points.txt
cult_cargo-0.2.0.dist-info/RECORD
