Metadata-Version: 2.3
Name: cult-cargo
Version: 0.2.0
Summary: Curated cargo of standard radio astronomy packages for stimela 2.x
License: MIT
Author: Oleg Smirnov, Sphesihle Makhathini
Requires-Python: >=3.9,<3.13
Classifier: License :: OSI Approved :: MIT License
Classifier: Programming Language :: Python :: 3
Classifier: Programming Language :: Python :: 3.9
Classifier: Programming Language :: Python :: 3.10
Classifier: Programming Language :: Python :: 3.11
Classifier: Programming Language :: Python :: 3.12
Requires-Dist: requests (>=2.0,<3.0)
Requires-Dist: stimela (>=2.1.1,<3.0.0)
